{
  "name": "Havidz Muhammad Iqbal",
  "email": "havidziqbal11@gmail.com",
  "phone": "082374982681",
  "education_level": "S1",
  "education_major": "Computer Science",
  "university": "University of Darussalam Gontor",
  "hard_skills": [
    "User Experience Interaction Design",
    "User Interface",
    "Physical and Digital Prototyping",
    "Visual Design",
    "Wireframing",
    "Low-High Fidelity Mockups",
    "Troubleshooting Hardware and Software Issues",
    "Technical Issue Resolution",
    "Lab Equipment Maintenance",
    "Figma",
    "Nition",
    "Photoshop",
    "Coreldraw",
    "Google Workspace",
    "Microsoft Office",
    "Canva",
    "Capcut",
    "Android Studio"
  ],
  "soft_skills": [
    "Leadership",
    "Lesson Planning and Implementation",
    "Hands-on Programming Guidance",
    "Student Assessment and Feedback",
    "Educational Technology Integration",
    "Classroom and Lab Management",
    "Financial Management and Reporting",
    "Project and Event Management",
    "Documentation and Reporting",
    "Social Media Management",
    "Event Coordination",
    "Content Creation and Curation",
    "Strategic Problem-Solving"
  ],
  "years_experience": 3.58,
  "certifications": [],
  "languages": [],
  "job_titles": [
    "Computer Teacher",
    "Mobile Developer",
    "Study Club Instructor",
    "Laboratory Assistant",
    "Assistant Lecturer",
    "IT Support and Management"
  ],
  "industries": [
    "Education",
    "Technology"
  ],
  "location": null
}