{
  "name": "LILIS APRILIANI",
  "email": "lilisapriliani24@gmail.com",
  "phone": "087820234173",
  "education_level": "S1",
  "education_major": "Agroteknologi",
  "university": "Universitas Siliwangi",
  "hard_skills": [
    "Microsoft Word",
    "Microsoft Excel",
    "Microsoft Power Point",
    "Google Docs",
    "Google Sheets"
  ],
  "soft_skills": [
    "Komunikasi yang baik",
    "Detail",
    "Teliti",
    "Adaptasi",
    "Event planning",
    "Administrasi",
    "Bekerja sama"
  ],
  "years_experience": 0.0,
  "certifications": [
    "Admin Maret 2024 - Pintarnya",
    "Mengolah Data Menggunakan Excel dan Google Sheets Agustus 2023 - BisaMahir"
  ],
  "languages": [
    "Indonesia",
    "Inggris"
  ],
  "job_titles": [
    "Staf Departemen Sosial Lingkungan",
    "Divisi Acara",
    "Divisi Liaison Officer (LO)"
  ],
  "industries": [],
  "location": "Garut"
}