{
  "name": "Rabela Br Sitepu",
  "email": "rabelasitepu27@gmail.com",
  "phone": "0857 6185 9154",
  "education_level": "S1",
  "education_major": "Ilmu Komunikasi",
  "university": "Universitas Syiah Kuala",
  "hard_skills": [
    "Public Speaking",
    "Writing",
    "Copywriter",
    "Content Writer",
    "Microsoft Office"
  ],
  "soft_skills": [
    "Kemampuan beradaptasi",
    "Negosiasi",
    "Berpikir kritis",
    "Bekerjasama dalam tim",
    "Manajemen waktu",
    "Penyelesaian masalah",
    "Kepemimpinan"
  ],
  "years_experience": 0.0,
  "certifications": [
    "Pelatihan SAGUSABU (S atu Guru S atu Buku) K ot a Binjai"
  ],
  "languages": [
    "Bahasa Indonesia"
  ],
  "job_titles": [
    "Mentor Sejarah",
    "MC",
    "Admin Instagram"
  ],
  "industries": [],
  "location": "Binjai"
}