{
  "name": "Ariel Delvanza Ramdhendy",
  "email": "arielramadhendy12@gmail.com",
  "phone": "+6281282730076",
  "education_level": "S1",
  "education_major": "Teknik Informatika",
  "university": "Universitas Krisnadwipayana",
  "hard_skills": [
    "Figma",
    "Canva"
  ],
  "soft_skills": [
    "Mampu berkomunikasi dengan baik",
    "Dapat bekerja dalam tim ataupun individu",
    "Mampu mengatur waktu dengan baik"
  ],
  "years_experience": 0.25,
  "certifications": [
    "Sertifikat Kelulusan: Studi Independen Peningkatan Keterampilan UI/UX (2024)",
    "Sertifikat Apresiasi: Peningkatan Keterampilan UI/UX (2024)",
    "Sertifikat Partisipasi: Kampus Merdeka Angkatan 7 (2024)"
  ],
  "languages": [
    "Bahasa Indonesia"
  ],
  "job_titles": [
    "UI/UX Desainer"
  ],
  "industries": [
    "Education"
  ],
  "location": "Jakarta"
}