{
  "name": "Muthia Novianti",
  "email": "muthia.novianti21@gmail.com",
  "phone": "+628176539746",
  "education_level": "S1",
  "education_major": "SISTEM INFORMASI",
  "university": "UNIVERSITAS BINA SARANA INFORMATIKA",
  "hard_skills": [
    "Microsoft Excel",
    "Microsoft Word",
    "Python",
    "tableu",
    "sistem informasi",
    "Accurate - Software Aplikasi",
    "Coretax",
    "E-commerce"
  ],
  "soft_skills": [
    "Adaptasi",
    "Adaptasi terhadap Perubahan",
    "Adaptasi Cepat"
  ],
  "years_experience": 6.416666666666667,
  "certifications": [],
  "languages": [],
  "job_titles": [
    "Admin Keuangan",
    "Admin Data Peserta",
    "Admin Social Media",
    "Petugas Kebersihan / Cleaning Service",
    "Cleaning Service",
    "Staff production EVENT DWP",
    "cook helper"
  ],
  "industries": [
    "Finance",
    "Training",
    "Food",
    "Service",
    "Healthcare",
    "Event"
  ],
  "location": "Jakarta Pusat"
}